sliderplot/__init__.py
sliderplot/sliderplot.py
sliderplot-0.1.1.dist-info/licenses/LICENSE
sliderplot-0.1.1.dist-info/METADATA
sliderplot-0.1.1.dist-info/WHEEL
sliderplot-0.1.1.dist-info/top_level.txt
sliderplot-0.1.1.dist-info/RECORD
