Metadata-Version: 2.4
Name: sliderplot
Version: 0.1.1
Summary: Turn a function into an interactive plot with a single line of code
Home-page: https://github.com/ngripon/sliderplot
Author: Nathan Gripon
Author-email: n.gripon@gmail.com
Project-URL: Bug Tracker, https://github.com/ngripon/sliderplot/issues
Classifier: Programming Language :: Python :: 3
Classifier: License :: OSI Approved :: MIT License
Classifier: Operating System :: OS Independent
Requires-Python: >=3.9
License-File: LICENSE
Requires-Dist: numpy
Requires-Dist: panel
Requires-Dist: bokeh
Requires-Dist: jupyter_bokeh
Dynamic: author
Dynamic: author-email
Dynamic: classifier
Dynamic: description
Dynamic: description-content-type
Dynamic: home-page
Dynamic: license-file
Dynamic: project-url
Dynamic: requires-dist
Dynamic: requires-python
Dynamic: summary
